CHANGELOG.rst
LICENSE
MANIFEST.in
README.rst
setup.py
praekelt/__init__.py
praekelt.recipe.backup.egg-info/PKG-INFO
praekelt.recipe.backup.egg-info/SOURCES.txt
praekelt.recipe.backup.egg-info/dependency_links.txt
praekelt.recipe.backup.egg-info/entry_points.txt
praekelt.recipe.backup.egg-info/not-zip-safe
praekelt.recipe.backup.egg-info/requires.txt
praekelt.recipe.backup.egg-info/top_level.txt
praekelt/recipe/__init__.py
praekelt/recipe/backup.py
praekelt/recipe/utils.py