Metadata-Version: 1.0
Name: praekelt.recipe.backup
Version: 0.0.3
Summary: Filesystem and database backup Buildout recipe.
Home-page: http://github.com/praekelt/praekelt.recipe.backup
Author: Praekelt Foundation
Author-email: dev@praekelt.com
License: BSD
Platform: UNKNOWN
Classifier: Programming Language :: Python
Classifier: License :: OSI Approved :: BSD License
Classifier: Development Status :: 4 - Beta
Classifier: Operating System :: OS Independent
Classifier: Framework :: Buildout
Classifier: Intended Audience :: Developers
Classifier: Topic :: Internet :: WWW/HTTP :: Dynamic Content
